UniTrain/__init__.py
UniTrain/train.py
UniTrain/dataset/DCGAN.py
UniTrain/dataset/__init__.py
UniTrain/dataset/classification.py
UniTrain/dataset/segmentation.py
UniTrain/models/DCGAN.py
UniTrain/models/__init__.py
UniTrain/models/classification.py
UniTrain/models/segmentation.py
UniTrain/utils/DCGAN.py
UniTrain/utils/__init__.py
UniTrain/utils/classification.py
UniTrain/utils/segmentation.py
UniTrain-0.2.4.dist-info/LICENSE
UniTrain-0.2.4.dist-info/METADATA
UniTrain-0.2.4.dist-info/WHEEL
UniTrain-0.2.4.dist-info/top_level.txt
UniTrain-0.2.4.dist-info/RECORD
