Metadata-Version: 2.1
Name: UniTrain
Version: 0.2.4
Summary: A generalized training framework for Deep Learning Tasks
Home-page: https://github.com/ishan121028/UniTrain
Download-URL: https://github.com/ishan121028/UniTrain/archive/v0.1.tar.gz
Author: Ishan Upadhyay
Author-email: ishan.upadhyay.iitb@gmail.com
Keywords: Deep Learning,Machine Learning,Training Framework
Classifier: Development Status :: 3 - Alpha
Classifier: Intended Audience :: Developers
Classifier: Intended Audience :: Education
Classifier: License :: OSI Approved :: MIT License
Classifier: Programming Language :: Python :: 3
Classifier: Programming Language :: Python :: 3.7
Classifier: Programming Language :: Python :: 3.8
Classifier: Programming Language :: Python :: 3.9
Classifier: Topic :: Scientific/Engineering :: Artificial Intelligence
License-File: LICENSE
Requires-Dist: torch
Requires-Dist: torchvision
Requires-Dist: numpy
Requires-Dist: pandas
Requires-Dist: torchsummary
Requires-Dist: opencv-python
